epibox/__init__.py
epibox/__main__.py
epibox/config_debug.py
epibox/common/__init__.py
epibox/common/create_folder.py
epibox/common/get_defaults.py
epibox/common/open_file.py
epibox/common/process_data.py
epibox/common/read_modules.py
epibox/common/run_system.py
epibox/common/setup.py
epibox/common/write_file.py
epibox/devices/__init__.py
epibox/devices/connect_device.py
epibox/devices/header.py
epibox/devices/manage_devices.py
epibox/exceptions/__init__.py
epibox/exceptions/exception_manager.py
epibox/exceptions/system_exceptions.py
epibox/mqtt_manager/__init__.py
epibox/mqtt_manager/message_handler.py
epibox/mqtt_manager/utils.py
epibox/run/__init__.py
epibox/run/run.py
epibox-3.0.0.dist-info/AUTHORS.rst
epibox-3.0.0.dist-info/LICENSE
epibox-3.0.0.dist-info/METADATA
epibox-3.0.0.dist-info/WHEEL
epibox-3.0.0.dist-info/entry_points.txt
epibox-3.0.0.dist-info/top_level.txt
epibox-3.0.0.dist-info/RECORD
