Metadata-Version: 2.1
Name: epibox
Version: 3.0.0
Summary: EpiBOX is a Raspberry Pi tool for easy signal acquisition.
Home-page: https://github.com/anascacais/epibox
Author: Ana Sofia Carmo
Author-email: anascacais@gmail.com
License: MIT license
Keywords: epibox,signal acquisition,Raspberry Pi
Classifier: Development Status :: 2 - Pre-Alpha
Classifier: Intended Audience :: Developers
Classifier: License :: OSI Approved :: MIT License
Classifier: Natural Language :: English
Classifier: Programming Language :: Python :: 3
Classifier: Programming Language :: Python :: 3.6
Classifier: Programming Language :: Python :: 3.7
Classifier: Programming Language :: Python :: 3.8
Requires-Python: >=3.6, <3.10
License-File: LICENSE
License-File: AUTHORS.rst
Requires-Dist: bitalino ==1.2.1
Requires-Dist: paho-mqtt ==1.5.1
Requires-Dist: pyserial ==3.5
Requires-Dist: scientisst-sense ==1.0.5
Requires-Dist: scipy
Requires-Dist: bump
Requires-Dist: pybluez2 ; sys_platform != "darwin"
Requires-Dist: numpy ==1.21.0 ; sys_platform != "win32"
Requires-Dist: numpy ; sys_platform == "win32"
Requires-Dist: pywin32 ; sys_platform == "win32"
